eo2py/__init__.py
eo2py/atoms.py
eo2py-0.1.7.dist-info/LICENSE
eo2py-0.1.7.dist-info/METADATA
eo2py-0.1.7.dist-info/WHEEL
eo2py-0.1.7.dist-info/top_level.txt
eo2py-0.1.7.dist-info/RECORD
