Metadata-Version: 2.1
Name: eo2py
Version: 0.1.7
Summary: Everything required to run Python files created by eo2py-maven-plugin
Home-page: https://github.com/polystat/eo2py
Author: Mikhail Olokin
Author-email: olomishcak@outlook.com
License: MIT
Project-URL: Bug Tracker, https://github.com/polystat/eo2py/issues
Platform: UNKNOWN
Classifier: Programming Language :: Python :: 3
Classifier: License :: OSI Approved :: MIT License
Classifier: Operating System :: OS Independent
Requires-Python: >=3.6
License-File: LICENSE
